LICENSE
MANIFEST.in
README.rst
setup.py
bee_django_crm/__init__.py
bee_django_crm/admin.py
bee_django_crm/apps.py
bee_django_crm/decorators.py
bee_django_crm/exports.py
bee_django_crm/forms.py
bee_django_crm/models.py
bee_django_crm/signals.py
bee_django_crm/tests.py
bee_django_crm/urls.py
bee_django_crm/utils.py
bee_django_crm/validators.py
bee_django_crm/views.py
bee_django_crm/wxapp.py
bee_django_crm/wxapp_urls.py
bee_django_crm.egg-info/.DS_Store
bee_django_crm.egg-info/PKG-INFO
bee_django_crm.egg-info/SOURCES.txt
bee_django_crm.egg-info/dependency_links.txt
bee_django_crm.egg-info/top_level.txt
bee_django_crm/management/.DS_Store
bee_django_crm/management/__init__.py
bee_django_crm/management/__init__.pyc
bee_django_crm/management/commands/__init__.py
bee_django_crm/management/commands/__init__.pyc
bee_django_crm/management/commands/init_city_db.py
bee_django_crm/management/commands/init_city_db.pyc
bee_django_crm/migrations/0001_initial.py
bee_django_crm/migrations/0001_initial.pyc
bee_django_crm/migrations/__init__.py
bee_django_crm/migrations/__init__.pyc
bee_django_crm/static/.DS_Store
bee_django_crm/static/bee_django_crm/bootstrap/css/bootstrap-theme.min.css
bee_django_crm/static/bee_django_crm/bootstrap/css/bootstrap.min.css
bee_django_crm/static/bee_django_crm/bootstrap/fonts/glyphicons-halflings-regular.eot
bee_django_crm/static/bee_django_crm/bootstrap/fonts/glyphicons-halflings-regular.svg
bee_django_crm/static/bee_django_crm/bootstrap/fonts/glyphicons-halflings-regular.ttf
bee_django_crm/static/bee_django_crm/bootstrap/fonts/glyphicons-halflings-regular.woff
bee_django_crm/static/bee_django_crm/bootstrap/fonts/glyphicons-halflings-regular.woff2
bee_django_crm/static/bee_django_crm/bootstrap/js/bootstrap.min.js
bee_django_crm/static/bee_django_crm/cityselect/css/main.css
bee_django_crm/static/bee_django_crm/cityselect/js/city.min.js
bee_django_crm/static/bee_django_crm/cityselect/js/jquery.cityselect.js
bee_django_crm/static/bee_django_crm/cityselect/js/jquery.js
bee_django_crm/static/bee_django_crm/css/css.css
bee_django_crm/static/bee_django_crm/css/css.html
bee_django_crm/static/bee_django_crm/data/city.json
